AUTHORS
CHANGELOG.rst
LICENSE
MANIFEST.in
README.md
setup.py
django_include_strip_tag.egg-info/PKG-INFO
django_include_strip_tag.egg-info/SOURCES.txt
django_include_strip_tag.egg-info/dependency_links.txt
django_include_strip_tag.egg-info/top_level.txt
django_include_strip_tag.egg-info/zip-safe
include_strip_tag/__init__.py
include_strip_tag/models.py
include_strip_tag/templatetags/__init__.py
include_strip_tag/templatetags/include_strip.py