Metadata-Version: 1.0
Name: django-include-strip-tag
Version: 0.1.0
Summary: A 'include_strip' templatetag for django to strip trailing and leading spaces/newlines
Home-page: https://github.com/twidi/django-include-strip-tag
Author: Stephane "Twidi" Angel
Author-email: s.angel@twidid.com
License: MIT
Download-URL: https://github.com/twidi/django-include-strip-tag/downloads
Keywords: django include templatetag template strip
Platform: any
Classifier: Development Status :: 3 - Alpha
Classifier: Environment :: Web Environment
Classifier: Intended Audience :: Developers
Classifier: License :: OSI Approved :: MIT License
Classifier: Operating System :: OS Independent
Classifier: Topic :: Software Development :: Libraries :: Python Modules
Classifier: Programming Language :: Python
Classifier: Framework :: Django
